chembridger/__init__.py
chembridger/dataset/Splitting.py
chembridger/dataset/__init__.py
chembridger/desc.py
chembridger/descriptor/Fingerprint.py
chembridger/descriptor/KS.py
chembridger/descriptor/Physicochemical.py
chembridger/descriptor/Similarity.py
chembridger/descriptor/__init__.py
chembridger/molecule/SDF.py
chembridger/molecule/SMILES.py
chembridger/molecule/__init__.py
chembridger/path.py
chembridger/smiles.py
chembridger/splitter.py
chembridger/util/Console.py
chembridger/util/__init__.py
chembridger-0.1.0.dist-info/LICENSE
chembridger-0.1.0.dist-info/METADATA
chembridger-0.1.0.dist-info/WHEEL
chembridger-0.1.0.dist-info/RECORD
