Metadata-Version: 2.3
Name: chembridger
Version: 0.1.0
Summary: 
Author: Jianfeng Sun
Author-email: jianfeng.sunmt@gmail.com
Requires-Python: >=3.12
Classifier: Programming Language :: Python :: 3
Classifier: Programming Language :: Python :: 3.12
Classifier: Programming Language :: Python :: 3.13
Requires-Dist: numpy (>=2.3.2,<3.0.0)
Requires-Dist: pandas (>=2.3.1,<3.0.0)
Requires-Dist: rdkit (>=2025.3.3,<2026.0.0)
Requires-Dist: tqdm (>=4.67.1,<5.0.0)
Requires-Dist: useful-rdkit-utils (>=0.89,<0.90)
